{
  "main": {
    "id": "d8a8509670004541",
    "type": "split",
    "children": [
      {
        "id": "9e1a0dedb907f3e7",
        "type": "tabs",
        "children": [
          {
            "id": "4a4de0cc7f85cf6f",
            "type": "leaf",
            "state": {
              "type": "markdown",
              "state": {
                "file": "深度学习/李宏毅机器学习/李宏毅机器学习教程.md",
                "mode": "source",
                "backlinks": false,
                "source": false
              }
            }
          }
        ]
      }
    ],
    "direction": "vertical"
  },
  "left": {
    "id": "0747c0bb6740f7d9",
    "type": "split",
    "children": [
      {
        "id": "28a26a9a86e76342",
        "type": "tabs",
        "children": [
          {
            "id": "5da566b1821a5ff8",
            "type": "leaf",
            "state": {
              "type": "file-explorer",
              "state": {
                "sortOrder": "alphabetical"
              }
            }
          },
          {
            "id": "be21afa696c94e38",
            "type": "leaf",
            "state": {
              "type": "search",
              "state": {
                "query": "pdf",
                "matchingCase": false,
                "explainSearch": false,
                "collapseAll": false,
                "extraContext": false,
                "sortOrder": "alphabetical"
              }
            }
          },
          {
            "id": "aec5822ef4969dba",
            "type": "leaf",
            "state": {
              "type": "starred",
              "state": {}
            }
          },
          {
            "id": "f9f410c9ea143633",
            "type": "leaf",
            "state": {
              "type": "outline",
              "state": {
                "file": "深度学习/李宏毅机器学习/李宏毅机器学习教程.md"
              }
            }
          },
          {
            "id": "b3aa56ef4fb88b0d",
            "type": "leaf",
            "state": {
              "type": "bookmarks",
              "state": {}
            }
          }
        ]
      }
    ],
    "direction": "horizontal",
    "width": 242.5,
    "collapsed": true
  },
  "right": {
    "id": "4113fa25b3c0a5ec",
    "type": "split",
    "children": [
      {
        "id": "2c1ade0ddc1fdbd5",
        "type": "tabs",
        "children": [
          {
            "id": "9f786da84384106a",
            "type": "leaf",
            "state": {
              "type": "backlink",
              "state": {
                "file": "深度学习/李宏毅机器学习/李宏毅机器学习教程.md",
                "collapseAll": false,
                "extraContext": false,
                "sortOrder": "alphabetical",
                "showSearch": false,
                "searchQuery": "",
                "backlinkCollapsed": false,
                "unlinkedCollapsed": true
              }
            }
          },
          {
            "id": "f539130e01e5ea60",
            "type": "leaf",
            "state": {
              "type": "outgoing-link",
              "state": {
                "file": "深度学习/李宏毅机器学习/李宏毅机器学习教程.md",
                "linksCollapsed": false,
                "unlinkedCollapsed": true
              }
            }
          },
          {
            "id": "6b51d387672c6841",
            "type": "leaf",
            "state": {
              "type": "tag",
              "state": {
                "sortOrder": "alphabetical",
                "useHierarchy": true
              }
            }
          },
          {
            "id": "d685ac07b0ce6589",
            "type": "leaf",
            "state": {
              "type": "advanced-tables-toolbar",
              "state": {}
            }
          }
        ],
        "currentTab": 2
      }
    ],
    "direction": "horizontal",
    "width": 300,
    "collapsed": true
  },
  "left-ribbon": {
    "hiddenItems": {
      "obsidian-excalidraw-plugin:Create new drawing": false,
      "switcher:Open quick switcher": false,
      "canvas:Create new canvas": false,
      "graph:Open graph view": false,
      "command-palette:Open command palette": false,
      "templates:Insert template": false,
      "random-note:Open random note": false,
      "table-editor-obsidian:Advanced Tables Toolbar": false
    }
  },
  "active": "4a4de0cc7f85cf6f",
  "lastOpenFiles": [
    "深度学习/李宏毅机器学习/_attachments/Pasted image 20230827232727.png",
    "深度学习/李宏毅机器学习/_attachments/Pasted image 20230827230531.png",
    "深度学习/李宏毅机器学习/_attachments/Pasted image 20230827230340.png",
    "深度学习/李宏毅机器学习/_attachments/Pasted image 20230827225719.png",
    "深度学习/李宏毅机器学习/_attachments/Pasted image 20230827225558.png",
    "深度学习/李宏毅机器学习/_attachments/Pasted image 20230827225532.png",
    "深度学习/李宏毅机器学习/_attachments/Pasted image 20230827225446.png",
    "深度学习/李宏毅机器学习/_attachments/Pasted image 20230827221805.png",
    "深度学习/李宏毅机器学习/_attachments/Pasted image 20230827215211.png",
    "深度学习/李宏毅机器学习/李宏毅机器学习教程.md",
    "深度学习/李宏毅机器学习/_attachments",
    "深度学习/李宏毅机器学习",
    "深度学习/_attachments",
    "深度学习/Pytorch.md",
    "深度学习/CodeGeeX2实践.md",
    "深度学习/动手学深度学习/动手学深度学习.md",
    "consistant-report.md",
    "深度学习/动手学深度学习/概念.md",
    "深度学习/动手学深度学习/_attachments/Pasted image 20230817204605.png",
    "深度学习/动手学深度学习/_attachments/Pasted image 20230817204630.png",
    "深度学习/动手学深度学习/Pasted image 20230817204630.png.md",
    "语言/Java/Effective Java/Effective_Java中文版(原书第3版)_by_Joshua_Bloch_(z-lib.org).pdf",
    "_attachment/Pasted image 20230505113538.png.md",
    "Excalidraw/Drawing 2023-06-27 22.09.28.excalidraw.md",
    "Excalidraw/Drawing 2023-03-18 23.22.05.excalidraw.md",
    "数据结构/魔方/一层一层的解决.md",
    "数据结构/魔方/魔方还原算法.md",
    "数据结构/魔方/在线.md",
    "深度学习",
    "语言/TypeScript/TypeScript.md",
    "语言/TypeScript/note.md",
    "深度学习/动手学深度学习/_attachments",
    "人工智能/AIDD/AIDD.md",
    "人工智能/AIDD/_attachments",
    "人工智能/AIDD",
    "人工智能/Prompt.md",
    "深度学习/动手学深度学习",
    "框架_中间件/后端/SpringCloud/SpringCloud.md",
    "工具/mac安装oh-my-zsh.md",
    "工具/git不再使用密码进行认证.md",
    "工具/github中的快速查找.md",
    "工具/github-clone慢.md",
    "工具/git命令.md",
    "语言/C++/cmake/cmake官方教程（搬运）/cmake官方教程（搬运）.md",
    "框架_中间件/后端/Spring/Bootstrap和application.md",
    "计算机基础/数据库/Es"
  ]
}